{
  "version": 4,
  "id": "case-work",
  "title": "케이스 워크, 삼각형 판별 의사결정 트리",
  "description": "3개 변 (a, b, c) 로 삼각형 성립 여부 + 종류 (정삼각형, 이등변, 직각, 일반) 판별. 조건 분기 트리.",
  "category": "algorithm",
  "tags": ["case-work", "foundation", "decision-tree"],
  "duration": 14000,
  "canvas": { "width": 900, "height": 500, "background": "transparent" },
  "elements": [
    { "type": "text", "id": "title", "rotation": 0, "x": 450, "y": 28, "content": "Case Work: 삼각형 판별 의사결정 트리", "fontSize": 20, "fontWeight": 700, "color": "#18181b", "textAnchor": "middle", "appearances": [{ "start": 0, "end": 14000 }], "tracks": [] },
    { "type": "text", "id": "step", "rotation": 0, "x": 450, "y": 58, "content": "입력: a=3, b=4, c=5", "fontSize": 14, "fontWeight": 600, "color": "#6366f1", "textAnchor": "middle", "appearances": [{ "start": 0, "end": 14000 }], "tracks": [
      { "property": "content", "keyframes": [
        { "time": 0, "value": "입력: a=3, b=4, c=5" },
        { "time": 2000, "value": "케이스 1: 삼각형 성립? a+b>c, b+c>a, c+a>b" },
        { "time": 4000, "value": "케이스 2: 정삼각형? a==b==c" },
        { "time": 6000, "value": "케이스 3: 이등변? a==b or b==c or c==a" },
        { "time": 8000, "value": "케이스 4: 직각? a²+b²==c²" },
        { "time": 10500, "value": "케이스 5: 일반 삼각형" },
        { "time": 12500, "value": "답: right (3²+4²=5²)" }
      ]}
    ]},
    { "type": "rect", "id": "root", "rotation": 0, "x": 350, "y": 110, "width": 200, "height": 50, "fill": "#dbeafe", "stroke": "#2563eb", "strokeWidth": 2, "cornerRadius": 8, "label": "삼각형 성립?", "labelColor": "#1e3a8a", "labelSize": 14, "subtitle": "a+b>c && ...", "subtitleSize": 11, "appearances": [{ "start": 0, "end": 14000 }], "tracks": [
      { "property": "fill", "keyframes": [
        { "time": 0, "value": "#dbeafe" },
        { "time": 2000, "value": "#dcfce7" }
      ]}
    ]},
    { "type": "rect", "id": "case1-no", "rotation": 0, "x": 100, "y": 180, "width": 150, "height": 40, "fill": "#fee2e2", "stroke": "#dc2626", "strokeWidth": 2, "cornerRadius": 6, "label": "NO → 불가능", "labelColor": "#7f1d1d", "labelSize": 13, "appearances": [{ "start": 2000, "end": 14000, "entryMode": "pop", "entryDuration": 300 }], "tracks": [] },
    { "type": "rect", "id": "case2", "rotation": 0, "x": 300, "y": 180, "width": 150, "height": 40, "fill": "#dbeafe", "stroke": "#2563eb", "strokeWidth": 2, "cornerRadius": 6, "label": "정삼각형?", "labelColor": "#1e3a8a", "labelSize": 13, "appearances": [{ "start": 4000, "end": 14000, "entryMode": "pop", "entryDuration": 300 }], "tracks": [
      { "property": "fill", "keyframes": [
        { "time": 0, "value": "#dbeafe" },
        { "time": 4000, "value": "#fef9c3" }
      ]}
    ]},
    { "type": "rect", "id": "case3", "rotation": 0, "x": 480, "y": 180, "width": 150, "height": 40, "fill": "#dbeafe", "stroke": "#2563eb", "strokeWidth": 2, "cornerRadius": 6, "label": "이등변?", "labelColor": "#1e3a8a", "labelSize": 13, "appearances": [{ "start": 6000, "end": 14000, "entryMode": "pop", "entryDuration": 300 }], "tracks": [
      { "property": "fill", "keyframes": [
        { "time": 0, "value": "#dbeafe" },
        { "time": 6000, "value": "#fef9c3" }
      ]}
    ]},
    { "type": "rect", "id": "case4", "rotation": 0, "x": 660, "y": 180, "width": 140, "height": 40, "fill": "#dbeafe", "stroke": "#2563eb", "strokeWidth": 2, "cornerRadius": 6, "label": "직각?", "labelColor": "#1e3a8a", "labelSize": 13, "appearances": [{ "start": 8000, "end": 14000, "entryMode": "pop", "entryDuration": 300 }], "tracks": [
      { "property": "fill", "keyframes": [
        { "time": 0, "value": "#dbeafe" },
        { "time": 8000, "value": "#dcfce7" }
      ]}
    ]},
    { "type": "rect", "id": "case4-yes", "rotation": 0, "x": 660, "y": 240, "width": 140, "height": 40, "fill": "#dcfce7", "stroke": "#16a34a", "strokeWidth": 2, "cornerRadius": 6, "label": "YES → right", "labelColor": "#14532d", "labelSize": 13, "appearances": [{ "start": 10500, "end": 14000, "entryMode": "pop", "entryDuration": 300 }], "tracks": [] },
    { "type": "rect", "id": "case5", "rotation": 0, "x": 300, "y": 300, "width": 300, "height": 50, "fill": "#e2e8f0", "stroke": "#475569", "strokeWidth": 2, "cornerRadius": 8, "label": "일반 삼각형 (scalene)", "labelColor": "#0b0b0f", "labelSize": 14, "appearances": [{ "start": 10500, "end": 14000, "entryMode": "fade", "entryDuration": 400 }], "tracks": [] },
    { "type": "text", "id": "tree-label", "rotation": 0, "x": 80, "y": 130, "content": "의사결정 트리", "fontSize": 12, "fontWeight": 700, "color": "#64748b", "textAnchor": "start", "appearances": [{ "start": 0, "end": 14000 }], "tracks": [] },
    { "type": "line", "id": "l1", "rotation": 0, "x1": 350, "y1": 160, "x2": 175, "y2": 180, "stroke": "#94a3b8", "strokeWidth": 2, "appearances": [{ "start": 2000, "end": 14000 }], "tracks": [] },
    { "type": "line", "id": "l2", "rotation": 0, "x1": 450, "y1": 160, "x2": 375, "y2": 180, "stroke": "#94a3b8", "strokeWidth": 2, "appearances": [{ "start": 4000, "end": 14000 }], "tracks": [] },
    { "type": "line", "id": "l3", "rotation": 0, "x1": 500, "y1": 160, "x2": 555, "y2": 180, "stroke": "#94a3b8", "strokeWidth": 2, "appearances": [{ "start": 6000, "end": 14000 }], "tracks": [] },
    { "type": "line", "id": "l4", "rotation": 0, "x1": 550, "y1": 160, "x2": 730, "y2": 180, "stroke": "#94a3b8", "strokeWidth": 2, "appearances": [{ "start": 8000, "end": 14000 }], "tracks": [] },
    { "type": "line", "id": "l5", "rotation": 0, "x1": 730, "y1": 220, "x2": 730, "y2": 240, "stroke": "#94a3b8", "strokeWidth": 2, "appearances": [{ "start": 10500, "end": 14000 }], "tracks": [] },
    { "type": "text", "id": "verdict", "rotation": 0, "x": 450, "y": 400, "content": "케이스 분류로 명확. 누락/중복 없음. O(1).", "fontSize": 14, "fontWeight": 700, "color": "#16a34a", "textAnchor": "middle", "appearances": [{ "start": 12500, "end": 14000, "entryMode": "fade", "entryDuration": 400 }], "tracks": [] }
  ],
  "chapters": [
    { "id": "ch1", "time": 0, "label": "초기", "subtitle": "입력 a,b,c" },
    { "id": "ch2", "time": 2000, "label": "삼각형 성립", "subtitle": "" },
    { "id": "ch3", "time": 4000, "label": "정삼각형?", "subtitle": "" },
    { "id": "ch4", "time": 6000, "label": "이등변?", "subtitle": "" },
    { "id": "ch5", "time": 8000, "label": "직각?", "subtitle": "" },
    { "id": "ch6", "time": 10500, "label": "답 도출", "subtitle": "right" },
    { "id": "ch7", "time": 12500, "label": "결론", "subtitle": "O(1)" }
  ],
  "effects": [
    { "type": "pulse", "id": "e1", "elementId": "root", "time": 2100, "scale": 1.1, "duration": 500 },
    { "type": "pulse", "id": "e2", "elementId": "case2", "time": 4100, "scale": 1.1, "duration": 500 },
    { "type": "pulse", "id": "e3", "elementId": "case4", "time": 8100, "scale": 1.1, "duration": 500 },
    { "type": "highlight", "id": "e4", "elementId": "case4-yes", "time": 10600, "color": "#86efac", "duration": 1200 }
  ],
  "settings": { "loop": true, "autoplay": true, "showCaption": false, "showChapterList": true }
}
