{
  "version": 4,
  "id": "divide-and-conquer",
  "title": "분할 정복 (Divide and Conquer)",
  "description": "배열 [5, 3, 8, 1, 2] 를 재귀적으로 분할하고 병합하여 정렬하는 과정",
  "category": "algorithm",
  "tags": ["divide-conquer", "merge-sort", "recursion", "sorting"],
  "duration": 12000,
  "canvas": {
    "width": 900,
    "height": 500,
    "background": "transparent"
  },
  "elements": [
    {
      "type": "text",
      "id": "title",
      "rotation": 0,
      "x": 450,
      "y": 30,
      "content": "분할 정복: 병합 정렬",
      "fontSize": 22,
      "fontWeight": 700,
      "color": "#18181b",
      "textAnchor": "middle",
      "appearances": [
        {
          "start": 0,
          "end": 12000,
          "entryMode": "fade",
          "entryDuration": 300,
          "exitDuration": 300
        }
      ],
      "tracks": []
    },
    {
      "type": "text",
      "id": "step-label",
      "rotation": 0,
      "x": 450,
      "y": 60,
      "content": "초기 배열",
      "fontSize": 16,
      "fontWeight": 600,
      "color": "#7c3aed",
      "textAnchor": "middle",
      "appearances": [
        {
          "start": 0,
          "end": 12000,
          "entryMode": "fade",
          "entryDuration": 300,
          "exitDuration": 300
        }
      ],
      "tracks": [
        {
          "property": "content",
          "keyframes": [
            { "time": 0, "value": "초기 배열" },
            { "time": 1500, "value": "Divide: 절반으로 분할" },
            { "time": 4000, "value": "Divide: 더 작게 분할" },
            { "time": 6500, "value": "Conquer: Base case 도달" },
            { "time": 8500, "value": "Combine: 병합하며 정렬" },
            { "time": 10500, "value": "완료: 정렬된 배열" },
            { "time": 12000, "value": "초기 배열" }
          ]
        }
      ]
    },
    {
      "type": "rect",
      "id": "arr0",
      "rotation": 0,
      "x": 300,
      "y": 100,
      "width": 300,
      "height": 60,
      "fill": "#dbeafe",
      "stroke": "#3b82f6",
      "strokeWidth": 2.5,
      "cornerRadius": 8,
      "label": "[5, 3, 8, 1, 2]",
      "labelColor": "#1e3a8a",
      "labelSize": 16,
      "appearances": [
        {
          "start": 0,
          "end": 12000,
          "entryMode": "fade",
          "entryDuration": 400
        }
      ],
      "tracks": []
    },
    {
      "type": "rect",
      "id": "arr1-left",
      "rotation": 0,
      "x": 150,
      "y": 200,
      "width": 180,
      "height": 50,
      "fill": "#e0e7ff",
      "stroke": "#6366f1",
      "strokeWidth": 2,
      "cornerRadius": 6,
      "label": "[5, 3, 8]",
      "labelColor": "#312e81",
      "labelSize": 14,
      "appearances": [
        {
          "start": 1500,
          "end": 12000,
          "entryMode": "slide-down",
          "entryDuration": 400
        }
      ],
      "tracks": []
    },
    {
      "type": "rect",
      "id": "arr1-right",
      "rotation": 0,
      "x": 570,
      "y": 200,
      "width": 140,
      "height": 50,
      "fill": "#e0e7ff",
      "stroke": "#6366f1",
      "strokeWidth": 2,
      "cornerRadius": 6,
      "label": "[1, 2]",
      "labelColor": "#312e81",
      "labelSize": 14,
      "appearances": [
        {
          "start": 2000,
          "end": 12000,
          "entryMode": "slide-down",
          "entryDuration": 400
        }
      ],
      "tracks": []
    },
    {
      "type": "rect",
      "id": "arr2-1",
      "rotation": 0,
      "x": 90,
      "y": 290,
      "width": 70,
      "height": 45,
      "fill": "#fef3c7",
      "stroke": "#d97706",
      "strokeWidth": 2,
      "cornerRadius": 4,
      "label": "[5]",
      "labelColor": "#713f12",
      "labelSize": 13,
      "appearances": [
        {
          "start": 4000,
          "end": 12000,
          "entryMode": "zoom",
          "entryDuration": 300
        }
      ],
      "tracks": []
    },
    {
      "type": "rect",
      "id": "arr2-2",
      "rotation": 0,
      "x": 180,
      "y": 290,
      "width": 100,
      "height": 45,
      "fill": "#fef3c7",
      "stroke": "#d97706",
      "strokeWidth": 2,
      "cornerRadius": 4,
      "label": "[3, 8]",
      "labelColor": "#713f12",
      "labelSize": 13,
      "appearances": [
        {
          "start": 4300,
          "end": 12000,
          "entryMode": "zoom",
          "entryDuration": 300
        }
      ],
      "tracks": []
    },
    {
      "type": "rect",
      "id": "arr2-3",
      "rotation": 0,
      "x": 540,
      "y": 290,
      "width": 70,
      "height": 45,
      "fill": "#fef3c7",
      "stroke": "#d97706",
      "strokeWidth": 2,
      "cornerRadius": 4,
      "label": "[1]",
      "labelColor": "#713f12",
      "labelSize": 13,
      "appearances": [
        {
          "start": 4600,
          "end": 12000,
          "entryMode": "zoom",
          "entryDuration": 300
        }
      ],
      "tracks": []
    },
    {
      "type": "rect",
      "id": "arr2-4",
      "rotation": 0,
      "x": 630,
      "y": 290,
      "width": 70,
      "height": 45,
      "fill": "#fef3c7",
      "stroke": "#d97706",
      "strokeWidth": 2,
      "cornerRadius": 4,
      "label": "[2]",
      "labelColor": "#713f12",
      "labelSize": 13,
      "appearances": [
        {
          "start": 4900,
          "end": 12000,
          "entryMode": "zoom",
          "entryDuration": 300
        }
      ],
      "tracks": []
    },
    {
      "type": "rect",
      "id": "merge1",
      "rotation": 0,
      "x": 180,
      "y": 370,
      "width": 100,
      "height": 45,
      "fill": "#dcfce7",
      "stroke": "#16a34a",
      "strokeWidth": 2,
      "cornerRadius": 4,
      "label": "[3, 8]",
      "labelColor": "#14532d",
      "labelSize": 13,
      "appearances": [
        {
          "start": 8500,
          "end": 12000,
          "entryMode": "fade",
          "entryDuration": 400
        }
      ],
      "tracks": []
    },
    {
      "type": "rect",
      "id": "merge2",
      "rotation": 0,
      "x": 540,
      "y": 370,
      "width": 160,
      "height": 45,
      "fill": "#dcfce7",
      "stroke": "#16a34a",
      "strokeWidth": 2,
      "cornerRadius": 4,
      "label": "[1, 2]",
      "labelColor": "#14532d",
      "labelSize": 13,
      "appearances": [
        {
          "start": 8800,
          "end": 12000,
          "entryMode": "fade",
          "entryDuration": 400
        }
      ],
      "tracks": []
    },
    {
      "type": "rect",
      "id": "final",
      "rotation": 0,
      "x": 300,
      "y": 440,
      "width": 300,
      "height": 50,
      "fill": "#86efac",
      "stroke": "#059669",
      "strokeWidth": 3,
      "cornerRadius": 8,
      "label": "[1, 2, 3, 5, 8]",
      "labelColor": "#14532d",
      "labelSize": 17,
      "appearances": [
        {
          "start": 10500,
          "end": 12000,
          "entryMode": "zoom",
          "entryDuration": 500
        }
      ],
      "tracks": []
    }
  ],
  "chapters": [
    {
      "id": "s1",
      "time": 0,
      "label": "초기 배열",
      "subtitle": "[5, 3, 8, 1, 2] 정렬 시작"
    },
    {
      "id": "s2",
      "time": 1500,
      "label": "1단계 분할",
      "subtitle": "[5,3,8] + [1,2] 로 분할"
    },
    {
      "id": "s3",
      "time": 4000,
      "label": "2단계 분할 (Base)",
      "subtitle": "크기 1, 2 까지 분할"
    },
    {
      "id": "s4",
      "time": 6500,
      "label": "Conquer",
      "subtitle": "Base case 도달, 정복 시작"
    },
    {
      "id": "s5",
      "time": 8500,
      "label": "Combine",
      "subtitle": "정렬하며 병합"
    },
    {
      "id": "s6",
      "time": 10500,
      "label": "완료",
      "subtitle": "O(N log N) 정렬 완료"
    }
  ],
  "effects": [
    {
      "type": "highlight",
      "id": "eff-1",
      "elementId": "arr0",
      "time": 1500,
      "color": "#facc15",
      "duration": 500
    },
    {
      "type": "pulse",
      "id": "eff-2",
      "elementId": "arr1-left",
      "time": 1800,
      "scale": 1.08,
      "duration": 400
    },
    {
      "type": "pulse",
      "id": "eff-3",
      "elementId": "arr1-right",
      "time": 2100,
      "scale": 1.08,
      "duration": 400
    },
    {
      "type": "highlight",
      "id": "eff-4",
      "elementId": "arr2-1",
      "time": 6500,
      "color": "#86efac",
      "duration": 600
    },
    {
      "type": "highlight",
      "id": "eff-5",
      "elementId": "arr2-2",
      "time": 6700,
      "color": "#86efac",
      "duration": 600
    },
    {
      "type": "highlight",
      "id": "eff-6",
      "elementId": "arr2-3",
      "time": 6900,
      "color": "#86efac",
      "duration": 600
    },
    {
      "type": "highlight",
      "id": "eff-7",
      "elementId": "arr2-4",
      "time": 7100,
      "color": "#86efac",
      "duration": 600
    },
    {
      "type": "pulse",
      "id": "eff-8",
      "elementId": "merge1",
      "time": 8700,
      "scale": 1.1,
      "duration": 500
    },
    {
      "type": "pulse",
      "id": "eff-9",
      "elementId": "merge2",
      "time": 9000,
      "scale": 1.1,
      "duration": 500
    },
    {
      "type": "highlight",
      "id": "eff-10",
      "elementId": "final",
      "time": 10700,
      "color": "#34d399",
      "duration": 800
    },
    {
      "type": "pulse",
      "id": "eff-11",
      "elementId": "final",
      "time": 11000,
      "scale": 1.15,
      "duration": 600
    }
  ],
  "settings": {
    "loop": true,
    "autoplay": true,
    "showCaption": false,
    "showChapterList": true
  }
}
