{
  "version": 4,
  "id": "pisano",
  "title": "피사노 주기 (Pisano Period)",
  "description": "피보나치 수열 F_n mod m 의 주기 π(m). π(3)=8, π(10)=60.",
  "category": "algorithm",
  "tags": ["pisano", "fibonacci", "number-theory", "math"],
  "duration": 14000,
  "canvas": { "width": 900, "height": 500, "background": "transparent" },
  "elements": [
    { "type": "text", "id": "title", "rotation": 0, "x": 450, "y": 28, "content": "Pisano Period: π(3) = 8", "fontSize": 20, "fontWeight": 700, "color": "#18181b", "textAnchor": "middle", "appearances": [{ "start": 0, "end": 14000 }], "tracks": [] },
    { "type": "text", "id": "subtitle", "rotation": 0, "x": 450, "y": 58, "content": "F_n mod 3 수열 주기 탐지", "fontSize": 14, "fontWeight": 600, "color": "#6366f1", "textAnchor": "middle", "appearances": [{ "start": 0, "end": 14000 }], "tracks": [
      { "property": "content", "keyframes": [
        { "time": 0, "value": "F_n mod 3 수열 주기 탐지" },
        { "time": 3000, "value": "주기: 0,1,1,2,0,2,2,1 반복 (8개)" },
        { "time": 6000, "value": "(F_8, F_9) = (0, 1) 재등장!" },
        { "time": 9000, "value": "π(3)=8, π(10)=60, π(10^k)=15·10^(k-1)" },
        { "time": 12000, "value": "F_n mod m = F_(n mod π(m)) mod m" }
      ]}
    ]},
    { "type": "circle", "id": "c0", "rotation": 0, "cx": 450, "cy": 250, "r": 22, "fill": "#3b82f6", "stroke": "#1e3a8a", "strokeWidth": 2, "label": "0", "labelColor": "#fff", "labelSize": 14, "appearances": [{ "start": 0, "end": 14000 }], "tracks": [] },
    { "type": "circle", "id": "c1", "rotation": 0, "cx": 540, "cy": 180, "r": 22, "fill": "#10b981", "stroke": "#14532d", "strokeWidth": 2, "label": "1", "labelColor": "#fff", "labelSize": 14, "appearances": [{ "start": 0, "end": 14000 }], "tracks": [] },
    { "type": "circle", "id": "c2", "rotation": 0, "cx": 580, "cy": 280, "r": 22, "fill": "#10b981", "stroke": "#14532d", "strokeWidth": 2, "label": "1", "labelColor": "#fff", "labelSize": 14, "appearances": [{ "start": 0, "end": 14000 }], "tracks": [] },
    { "type": "circle", "id": "c3", "rotation": 0, "cx": 520, "cy": 360, "r": 22, "fill": "#f59e0b", "stroke": "#713f12", "strokeWidth": 2, "label": "2", "labelColor": "#fff", "labelSize": 14, "appearances": [{ "start": 0, "end": 14000 }], "tracks": [] },
    { "type": "circle", "id": "c4", "rotation": 0, "cx": 420, "cy": 360, "r": 22, "fill": "#3b82f6", "stroke": "#1e3a8a", "strokeWidth": 2, "label": "0", "labelColor": "#fff", "labelSize": 14, "appearances": [{ "start": 0, "end": 14000 }], "tracks": [] },
    { "type": "circle", "id": "c5", "rotation": 0, "cx": 360, "cy": 280, "r": 22, "fill": "#f59e0b", "stroke": "#713f12", "strokeWidth": 2, "label": "2", "labelColor": "#fff", "labelSize": 14, "appearances": [{ "start": 0, "end": 14000 }], "tracks": [] },
    { "type": "circle", "id": "c6", "rotation": 0, "cx": 320, "cy": 180, "r": 22, "fill": "#f59e0b", "stroke": "#713f12", "strokeWidth": 2, "label": "2", "labelColor": "#fff", "labelSize": 14, "appearances": [{ "start": 0, "end": 14000 }], "tracks": [] },
    { "type": "circle", "id": "c7", "rotation": 0, "cx": 380, "cy": 140, "r": 22, "fill": "#10b981", "stroke": "#14532d", "strokeWidth": 2, "label": "1", "labelColor": "#fff", "labelSize": 14, "appearances": [{ "start": 0, "end": 14000 }], "tracks": [] },
    { "type": "circle", "id": "cursor", "rotation": 0, "cx": 450, "cy": 250, "r": 28, "fill": "transparent", "stroke": "#dc2626", "strokeWidth": 4, "label": "", "labelColor": "", "labelSize": 0, "appearances": [{ "start": 2000, "end": 14000, "entryMode": "fade", "entryDuration": 300 }], "tracks": [
      { "property": "cx", "keyframes": [
        { "time": 2000, "value": 450 },
        { "time": 2600, "value": 540 },
        { "time": 3200, "value": 580 },
        { "time": 3800, "value": 520 },
        { "time": 4400, "value": 420 },
        { "time": 5000, "value": 360 },
        { "time": 5600, "value": 320 },
        { "time": 6200, "value": 380 },
        { "time": 6800, "value": 450 }
      ]},
      { "property": "cy", "keyframes": [
        { "time": 2000, "value": 250 },
        { "time": 2600, "value": 180 },
        { "time": 3200, "value": 280 },
        { "time": 3800, "value": 360 },
        { "time": 4400, "value": 360 },
        { "time": 5000, "value": 280 },
        { "time": 5600, "value": 180 },
        { "time": 6200, "value": 140 },
        { "time": 6800, "value": 250 }
      ]}
    ]},
    { "type": "rect", "id": "table-box", "rotation": 0, "x": 50, "y": 420, "width": 800, "height": 60, "fill": "#fef9c3", "stroke": "#eab308", "strokeWidth": 2, "cornerRadius": 8, "label": "π(2)=3, π(3)=8, π(5)=20, π(10)=60, π(10^k)=15·10^(k-1)", "labelColor": "#713f12", "labelSize": 13, "appearances": [{ "start": 8000, "end": 14000, "entryMode": "fade", "entryDuration": 400 }], "tracks": [] },
    { "type": "text", "id": "insight-text", "rotation": 0, "x": 100, "y": 110, "content": "(F_0, F_1) = (0, 1)", "fontSize": 12, "fontWeight": 600, "color": "#1e3a8a", "textAnchor": "start", "appearances": [{ "start": 1000, "end": 14000 }], "tracks": [] },
    { "type": "text", "id": "insight-text2", "rotation": 0, "x": 650, "y": 110, "content": "(F_8, F_9) = (0, 1)", "fontSize": 12, "fontWeight": 600, "color": "#dc2626", "textAnchor": "start", "appearances": [{ "start": 7000, "end": 14000, "entryMode": "fade", "entryDuration": 400 }], "tracks": [] },
    { "type": "text", "id": "application", "rotation": 0, "x": 450, "y": 395, "content": "활용: F_1000 mod 3 = F_(1000 mod 8) mod 3 = F_0 mod 3 = 0", "fontSize": 11, "color": "#475569", "textAnchor": "middle", "appearances": [{ "start": 10000, "end": 14000, "entryMode": "fade", "entryDuration": 400 }], "tracks": [] }
  ],
  "chapters": [
    { "id": "c1", "time": 0, "label": "Fibonacci mod 3", "subtitle": "원형 배치" },
    { "id": "c2", "time": 2000, "label": "주기 탐지", "subtitle": "커서 순환" },
    { "id": "c3", "time": 6800, "label": "(0,1) 재등장", "subtitle": "π(3) = 8" },
    { "id": "c4", "time": 8000, "label": "알려진 주기들", "subtitle": "π(10)=60 등" },
    { "id": "c5", "time": 10000, "label": "활용", "subtitle": "큰 n 축소" }
  ],
  "effects": [
    { "type": "highlight", "id": "e1", "elementId": "c0", "time": 2200, "color": "#facc15", "duration": 400 },
    { "type": "highlight", "id": "e2", "elementId": "c1", "time": 2800, "color": "#facc15", "duration": 400 },
    { "type": "pulse", "id": "e3", "elementId": "cursor", "time": 6900, "scale": 1.15, "duration": 600 },
    { "type": "highlight", "id": "e4", "elementId": "table-box", "time": 8200, "color": "#facc15", "duration": 800 },
    { "type": "pulse", "id": "e5", "elementId": "application", "time": 10200, "scale": 1.05, "duration": 500 }
  ],
  "settings": { "loop": true, "autoplay": true, "showCaption": false, "showChapterList": true }
}
