{
  "version": 4,
  "id": "ternary-search",
  "title": "삼분 탐색, 단봉 함수 극값",
  "description": "f(x) = -(x-5)^2 + 10 (포물선) 에서 최대값 찾기. m1, m2 비교 -> 1/3 구간 제거.",
  "category": "algorithm",
  "tags": ["ternary-search", "optimization", "unimodal", "algorithm"],
  "duration": 13000,
  "canvas": { "width": 900, "height": 500, "background": "transparent" },
  "elements": [
    { "type": "text", "id": "title", "rotation": 0, "x": 450, "y": 28, "content": "삼분 탐색: 단봉 함수 f(x) = -(x-5)^2 + 10", "fontSize": 19, "fontWeight": 700, "color": "#18181b", "textAnchor": "middle", "appearances": [{ "start": 0, "end": 13000 }], "tracks": [] },
    { "type": "text", "id": "step", "rotation": 0, "x": 450, "y": 58, "content": "초기 lo=0, hi=10", "fontSize": 14, "fontWeight": 600, "color": "#6366f1", "textAnchor": "middle", "appearances": [{ "start": 0, "end": 13000 }], "tracks": [
      { "property": "content", "keyframes": [
        { "time": 0, "value": "초기 [0, 10]. m1=3.33, m2=6.67" },
        { "time": 2500, "value": "f(m1)=7.22 < f(m2)=7.22 -> lo=3.33 (실제론 유사하지만 m2 쪽 선택)" },
        { "time": 5000, "value": "구간 [3.33, 10]. m1=5.56, m2=7.78" },
        { "time": 7500, "value": "f(m1) > f(m2) -> hi=7.78" },
        { "time": 10000, "value": "100회 반복 후 x ≈ 5.0" },
        { "time": 11500, "value": "극대 = (5.0, 10.0)" }
      ]}
    ]},
    { "type": "path", "id": "curve", "rotation": 0, "d": "M 120,400 Q 450,120 780,400", "fill": "none", "stroke": "#2563eb", "strokeWidth": 3, "appearances": [{ "start": 0, "end": 13000 }], "tracks": [] },
    { "type": "circle", "id": "peak", "rotation": 0, "x": 450, "y": 120, "radius": 8, "fill": "#dc2626", "stroke": "#7f1d1d", "strokeWidth": 2, "appearances": [{ "start": 10000, "end": 13000, "entryMode": "fade", "entryDuration": 400 }], "tracks": [] },
    { "type": "text", "id": "peak-label", "rotation": 0, "x": 450, "y": 100, "content": "(5, 10)", "fontSize": 13, "fontWeight": 700, "color": "#dc2626", "textAnchor": "middle", "appearances": [{ "start": 10000, "end": 13000, "entryMode": "fade", "entryDuration": 400 }], "tracks": [] },
    { "type": "line", "id": "lo-line", "rotation": 0, "x1": 120, "y1": 420, "x2": 120, "y2": 390, "stroke": "#16a34a", "strokeWidth": 3, "appearances": [{ "start": 0, "end": 13000 }], "tracks": [
      { "property": "x1", "keyframes": [
        { "time": 0, "value": 120 },
        { "time": 2500, "value": 230 }
      ]},
      { "property": "x2", "keyframes": [
        { "time": 0, "value": 120 },
        { "time": 2500, "value": 230 }
      ]}
    ]},
    { "type": "text", "id": "lo-label", "rotation": 0, "x": 120, "y": 440, "content": "lo=0", "fontSize": 13, "fontWeight": 700, "color": "#16a34a", "textAnchor": "middle", "appearances": [{ "start": 0, "end": 13000 }], "tracks": [
      { "property": "x", "keyframes": [
        { "time": 0, "value": 120 },
        { "time": 2500, "value": 230 }
      ]},
      { "property": "content", "keyframes": [
        { "time": 0, "value": "lo=0" },
        { "time": 2500, "value": "lo=3.3" }
      ]}
    ]},
    { "type": "line", "id": "hi-line", "rotation": 0, "x1": 780, "y1": 420, "x2": 780, "y2": 390, "stroke": "#dc2626", "strokeWidth": 3, "appearances": [{ "start": 0, "end": 13000 }], "tracks": [
      { "property": "x1", "keyframes": [
        { "time": 0, "value": 780 },
        { "time": 7500, "value": 560 }
      ]},
      { "property": "x2", "keyframes": [
        { "time": 0, "value": 780 },
        { "time": 7500, "value": 560 }
      ]}
    ]},
    { "type": "text", "id": "hi-label", "rotation": 0, "x": 780, "y": 440, "content": "hi=10", "fontSize": 13, "fontWeight": 700, "color": "#dc2626", "textAnchor": "middle", "appearances": [{ "start": 0, "end": 13000 }], "tracks": [
      { "property": "x", "keyframes": [
        { "time": 0, "value": 780 },
        { "time": 7500, "value": 560 }
      ]},
      { "property": "content", "keyframes": [
        { "time": 0, "value": "hi=10" },
        { "time": 7500, "value": "hi=7.8" }
      ]}
    ]},
    { "type": "circle", "id": "m1", "rotation": 0, "x": 340, "y": 250, "radius": 7, "fill": "#fef9c3", "stroke": "#eab308", "strokeWidth": 2, "appearances": [{ "start": 500, "end": 2500, "entryMode": "fade", "entryDuration": 300 }], "tracks": [] },
    { "type": "text", "id": "m1-label", "rotation": 0, "x": 340, "y": 230, "content": "m1", "fontSize": 12, "fontWeight": 600, "color": "#713f12", "textAnchor": "middle", "appearances": [{ "start": 500, "end": 2500 }], "tracks": [] },
    { "type": "circle", "id": "m2", "rotation": 0, "x": 560, "y": 250, "radius": 7, "fill": "#fef9c3", "stroke": "#eab308", "strokeWidth": 2, "appearances": [{ "start": 500, "end": 2500, "entryMode": "fade", "entryDuration": 300 }], "tracks": [] },
    { "type": "text", "id": "m2-label", "rotation": 0, "x": 560, "y": 230, "content": "m2", "fontSize": 12, "fontWeight": 600, "color": "#713f12", "textAnchor": "middle", "appearances": [{ "start": 500, "end": 2500 }], "tracks": [] },
    { "type": "circle", "id": "m1-2", "rotation": 0, "x": 360, "y": 210, "radius": 7, "fill": "#fef9c3", "stroke": "#eab308", "strokeWidth": 2, "appearances": [{ "start": 5000, "end": 7500, "entryMode": "fade", "entryDuration": 300 }], "tracks": [] },
    { "type": "circle", "id": "m2-2", "rotation": 0, "x": 520, "y": 180, "radius": 7, "fill": "#fef9c3", "stroke": "#eab308", "strokeWidth": 2, "appearances": [{ "start": 5000, "end": 7500, "entryMode": "fade", "entryDuration": 300 }], "tracks": [] },
    { "type": "rect", "id": "summary", "rotation": 0, "x": 250, "y": 450, "width": 400, "height": 40, "fill": "#f0fdf4", "stroke": "#16a34a", "strokeWidth": 2, "cornerRadius": 8, "label": "극대 = (5.0, 10.0), O(log N)", "labelColor": "#14532d", "labelSize": 14, "appearances": [{ "start": 11500, "end": 13000, "entryMode": "fade", "entryDuration": 400 }], "tracks": [] }
  ],
  "chapters": [
    { "id": "c1", "time": 0, "label": "초기 [0,10]", "subtitle": "" },
    { "id": "c2", "time": 2500, "label": "m1 < m2", "subtitle": "lo=3.3" },
    { "id": "c3", "time": 5000, "label": "구간 좁히기", "subtitle": "" },
    { "id": "c4", "time": 7500, "label": "hi=7.8", "subtitle": "" },
    { "id": "c5", "time": 10000, "label": "수렴", "subtitle": "x≈5" },
    { "id": "c6", "time": 11500, "label": "결과", "subtitle": "" }
  ],
  "effects": [
    { "type": "highlight", "id": "e1", "elementId": "m1", "time": 700, "color": "#facc15", "duration": 1200 },
    { "type": "highlight", "id": "e2", "elementId": "m2", "time": 700, "color": "#facc15", "duration": 1200 },
    { "type": "highlight", "id": "e3", "elementId": "m1-2", "time": 5200, "color": "#facc15", "duration": 1200 },
    { "type": "highlight", "id": "e4", "elementId": "m2-2", "time": 5200, "color": "#facc15", "duration": 1200 },
    { "type": "pulse", "id": "e5", "elementId": "peak", "time": 10200, "scale": 1.3, "duration": 700 },
    { "type": "pulse", "id": "e6", "elementId": "summary", "time": 11700, "scale": 1.04, "duration": 600 }
  ],
  "settings": { "loop": true, "autoplay": true, "showCaption": false, "showChapterList": true }
}
